[
    {"num": 1, "min_points": 90, "max_points": 100, "chance": 0,  "rname": "легендарное", "aura": "(Легенда)",   "colour": "y", "extra": "nosac nopurge", "weeks": 2 },
    {"num": 2, "min_points": 70, "max_points": 80,  "chance": 2,  "rname": "эпическое",   "aura": "(Эпик)",      "colour": "M", "extra": "", "weeks": 5 },
    {"num": 3, "min_points": 50, "max_points": 60,  "chance": 15, "rname": "редкое",      "aura": "(Редкое)",    "colour": "Y", "extra": "", "weeks": 10 },
    {"num": 4, "min_points": 30, "max_points": 40,  "chance": 35, "rname": "необычное",   "aura": "(Необычное)", "colour": "B",  "extra": ""},
    {"num": 5, "min_points": 0,  "max_points": 20,  "chance": 100, "rname": "обычное",     "aura": "",            "colour": "", "extra": ""}
]
