<?xml version="1.0" encoding="UTF-8"?>
<Command>
  <aliases l="en">gift</aliases>
  <aliases l="ru">подарить</aliases>
  <aliases l="ua">подарувати</aliases>
  <cat>item</cat>
  <help id="5024" level="-1" refby="get" type="CommandHelp">
  </help>
  <hint l="en">give an item to someone</hint>
  <hint l="ru">подарить кому-то вещь</hint>
  <hint l="ua">подарувати комусь річ</hint>
  <name l="en">present</name>
  <name l="ru">дарить</name>
  <name l="ua">дарувати</name>
  <order>player_only</order>
  <position>rest</position>
</Command>
