<?xml version="1.0" encoding="UTF-8"?>
<Command>
  <cat>move</cat>
  <extra>keep_hide</extra>
  <help id="1078" keyword="SPEEDWALK СПИДВОЛК" level="-1" type="CommandHelp">%FMT% *%CMD%* _маршрут_

Команда *%CMD%* используется для быстрого пробега по заданному маршруту.
Любое препятствие, например, закрытые двери или ловушки, останавливает бег.

Маршрут может состоять из:
%A% большая буква направления (NSEWDU), означает бег до упора в данном
  направлении. Наткнувшись на препятствие (стенку, запертую дверь),
  ты продолжишь двигаться по остальной части маршрута.
  Например: *%CMD%* N или *%CMD%* С (бежать до упора на север) 
            *%CMD%* Ed или *%CMD%* Во (бежать на восток пока не упремся, потом вниз)

%A% маленькая буква направления (nsewdu), означает один шаг в данном
  направлении. Ей может предшествовать число, означающее количество
  шагов, которые надо сделать в данном направлении.
  Например: *%CMD%* 30e5nSd8sn или *%CMD%* 30в5сЮо8юс
</help>
  <hint>побежать по заданному маршруту</hint>
  <name>run</name>
  <position>sleep</position>
  <russian>
    <node>бежать</node>
    <node>бег</node>
  </russian>
</Command>
