<?xml version="1.0" encoding="UTF-8"?>
<Race type="DefaultRace">
  <act>npc sentinel</act>
  <aff>swim regeneration slow</aff>
  <affects registry="skill">slow swim regeneration</affects>
  <form>blob amphibian cold_blood</form>
  <imm>mental disease</imm>
  <nameFemale>беспозвоночная</nameFemale>
  <nameMale>беспозвоночный</nameMale>
  <nameMlt>беспозвоночные</nameMlt>
  <nameNeuter>беспозвоночное</nameNeuter>
  <parts>guts eye eyestalks tentacles</parts>
  <res>charm weapon</res>
  <size>medium</size>
  <stats>
    <str>2</str>
    <int>-3</int>
    <wis>5</wis>
    <dex>-6</dex>
    <con>5</con>
    <cha>-4</cha>
  </stats>
  <vuln>fire cold</vuln>
  <wearloc registry="wearlocation">body about float</wearloc>
</Race>
