<?xml version="1.0" encoding="UTF-8"?>
<NoteThread>
  <command type="NoteCommand">
    <cat>note</cat>
    <extra>keep_hide ghost</extra>
    <hint l="en"></hint>
    <hint l="ru">истории, рассказы, стихи, поэмы</hint>
    <hint l="ua"></hint>
    <name l="en">story</name>
    <name l="ru">история</name>
    <name l="ua"></name>
    <order>never</order>
    <position>dead</position>
    <xaliases l="en"></xaliases>
    <xaliases l="ru"></xaliases>
    <xaliases l="ua"></xaliases>
  </command>
  <gender>female</gender>
  <keepDays>0</keepDays>
  <name>story</name>
  <nameMlt>stories</nameMlt>
  <readLevel>0</readLevel>
  <rusName>истори|я|и|и|ю|ей|и</rusName>
  <rusNameMlt>истори|и|й|ям|и|ями|ях</rusNameMlt>
  <writeLevel>0</writeLevel>
</NoteThread>
