<?xml version="1.0" encoding="UTF-8"?>
<skill type="GenericSkill">
  <affect type="DefaultAffectHandler">
    <wearoff>Твои глаза перестают слезиться от дыма.</wearoff>
  </affect>
  <beats>24</beats>
  <dammsg mg="n">огненное дыхание</dammsg>
  <group>draconian</group>
  <help id="658" level="-1" type="SkillHelp">Излюбленное развлечение драконов - пульнуть в тебя воронкой бушующего огня.
Попав под струю огня, жертва не только получит повреждения, но может и на время
ослепнут от дыма. Вещи в инвентаре испортятся от воздействия огня.
Часть этой могущественной магии доступна ведьмам и варлокам.

%SA% %H% [(dragons breath,дыхание драконов)]
</help>
  <mana>200</mana>
  <mob>
    <forbidden>false</forbidden>
    <ordered>true</ordered>
    <professional>true</professional>
  </mob>
  <nameRus>огненное дыхание</nameRus>
  <spell type="SPELL(FireBreath)">
    <casted>true</casted>
    <position>fight</position>
    <target>char_room</target>
    <type>offensive</type>
  </spell>
</skill>
