<?xml version="1.0" encoding="UTF-8"?>
<skill type="GenericSkill">
  <classes>
    <node name="anti-paladin">
      <level>1</level>
      <maximum>100</maximum>
      <rating>1</rating>
    </node>
    <node name="cleric">
      <level>1</level>
      <maximum>100</maximum>
      <rating>1</rating>
    </node>
    <node name="druid">
      <level>1</level>
      <maximum>100</maximum>
      <rating>1</rating>
    </node>
    <node name="necromancer">
      <level>1</level>
      <maximum>100</maximum>
      <rating>1</rating>
    </node>
    <node name="ninja">
      <level>1</level>
      <maximum>100</maximum>
      <rating>1</rating>
    </node>
    <node name="paladin">
      <level>1</level>
      <maximum>100</maximum>
      <rating>1</rating>
    </node>
    <node name="ranger">
      <level>1</level>
      <maximum>100</maximum>
      <rating>1</rating>
    </node>
    <node name="samurai">
      <level>1</level>
      <maximum>100</maximum>
      <rating>1</rating>
    </node>
    <node name="thief">
      <level>1</level>
      <maximum>100</maximum>
      <rating>1</rating>
    </node>
    <node name="vampire">
      <level>1</level>
      <maximum>100</maximum>
      <rating>1</rating>
    </node>
    <node name="warlock">
      <level>1</level>
      <maximum>100</maximum>
      <rating>1</rating>
    </node>
    <node name="warrior">
      <level>1</level>
      <maximum>100</maximum>
      <rating>1</rating>
    </node>
    <node name="witch">
      <level>1</level>
      <maximum>100</maximum>
      <rating>2</rating>
    </node>
  </classes>
  <dammsg mg="m"></dammsg>
  <group registry="skillGroup">fightmaster</group>
  <help id="585" level="-1" type="SkillHelp">
    <extra l="en">unarmed</extra>
    <extra l="ru">безоружный</extra>
    <extra l="ua">беззбройний</extra>
    <text l="en">The art of hand-to-hand combat is one of the most common in the Dreamland. 
One of the advantages of the style is that it is very difficult to disarm a warrior using it. Experienced hand-to-hand combat masters pose serious competition to swordmasters. The skill is available to almost all classes. Although not everyone uses it equally effectively.</text>
    <text l="ru">Искусство рукопашного боя одно из самых распространенных в Стране Грез. 
Одним из достоинств стиля является то, что обезоружить пользующегося им 
воина очень трудно. Опытные мастера рукопашного боя составляют серьезную 
конкуренцию мастерам-мечникам. Умение доступно почти всем классам. 
Хотя и не все используют его одинаково эффективно.
</text>
    <text l="ua">Мистецтво рукопашного бою є одним з найпоширеніших у Країні Снів. 
Однією з переваг стилю є те, що роззброїти воїна, який ним користується, дуже важко. Досвідчені майстри рукопашного бою складають серйозну конкуренцію майстрам-мечникам. Уміння доступне майже всім класам. 
Хоча не всі використовують його однаково ефективно.
</text>
  </help>
  <mob>
    <bonus>40</bonus>
    <dice>2</dice>
    <professional>false</professional>
  </mob>
  <name l="en">hand to hand</name>
  <name l="ru">рукопашный бой</name>
  <name l="ua">рукопашний бій</name>
  <raceBonuses registry="race">felar</raceBonuses>
</skill>