<?xml version="1.0" encoding="UTF-8"?>
<skill type="GenericSkill">
  <affect type="DefaultAffectHandler">
    <wearoff>Ты чувствуешь желание вознести молитву Богам.</wearoff>
  </affect>
  <align>good</align>
  <beats>12</beats>
  <classes>
    <node name="paladin">
      <level>10</level>
      <maximum>100</maximum>
      <rating>1</rating>
    </node>
  </classes>
  <dammsg></dammsg>
  <group registry="skillGroup">benedictions</group>
  <help id="843" level="-1" type="SkillHelp">%FMT% *%SPELL%*

Творя литургию Богам, паладин может получить божественную защиту, похожую на
ослабленную версию {hh656защиты святилища{x. Впридачу, если применить литургию в бою,
то Боги покарают жертву мощным боевым заклинанием, {hh831слепотой{x или {hh548проклятием{x.
А прочитанная перед боем литургия усилит {hh2036уровень{x и процент {hh1359владения{x
умениями паладина.

К сожалению, литургия -- занятие утомительное и истощающее. Сотворить литургию
можно только будучи полным сил -- здоровья, энергии и движения. К тому же,
неопытные в этом умении паладины могут разгневать Богов. Первое проявление
божественного гнева -- {hh704слабость{x, а если продолжать упорствовать -- Боги
насылают нездоровый {hh741сон{x, чтобы не доставали.
</help>
  <mana>100</mana>
  <nameRus>литургия</nameRus>
  <spell type="SPELL(Prayer)">
    <damtype>none</damtype>
    <flags>prayer</flags>
    <order>player_only</order>
    <position>fight</position>
    <target>char_self</target>
    <type>none</type>
  </spell>
</skill>
