<?xml version="1.0" encoding="UTF-8"?>
<Social type="Social">
  <msgCharAuto>Ты тянешь себя за волосы, но они не расчесываются.</msgCharAuto>
  <msgCharFound>Ты терпеливо распутываешь волосы $C2.</msgCharFound>
  <msgCharFound2></msgCharFound2>
  <msgCharNoArgument>Ты расчесываешь свои волосы.</msgCharNoArgument>
  <msgCharNotFound>Таких здесь нет.</msgCharNotFound>
  <msgOthersAuto>$c1 пытается прочесать свои патлы.</msgOthersAuto>
  <msgOthersFound>$c1 пытается прочесать спутанные волосы $C2.</msgOthersFound>
  <msgOthersFound2></msgOthersFound2>
  <msgOthersNoArgument>$c1 расчесывает свои волосы.</msgOthersNoArgument>
  <msgVictimFound>$c1 тянет тебя за волосы, желая расчесать их.</msgVictimFound>
  <msgVictimFound2></msgVictimFound2>
  <position>rest</position>
  <rusName>расчесать</rusName>
  <shortDesc>расчесывать волосы</shortDesc>
</Social>
