<?xml version="1.0" encoding="UTF-8"?>
<Social type="Social">
  <msgCharAuto>На самом деле тебе этого не очень хочется.</msgCharAuto>
  <msgCharFound>Ты оцениваешь $s по десятибальной системе.</msgCharFound>
  <msgCharNoArgument>Кого?</msgCharNoArgument>
  <msgCharNotFound>Сейчас их тут нет.</msgCharNotFound>
  <msgOthersAuto></msgOthersAuto>
  <msgOthersFound>$c1 считает $C4 полным нулем по десятибальной системе!!!</msgOthersFound>
  <msgOthersNoArgument></msgOthersNoArgument>
  <msgVictimFound>$c1 оценивает твои действия по десятибальной системе. Ты тянешь на ноль!!!</msgVictimFound>
  <position>rest</position>
  <rusName>заценить</rusName>
  <shortDesc>унизительно отозваться о ближнем своем</shortDesc>
</Social>
