<?xml version="1.0" encoding="UTF-8"?>
<Social type="Social">
  <msgCharAuto></msgCharAuto>
  <msgCharFound></msgCharFound>
  <msgCharFound2></msgCharFound2>
  <msgCharNoArgument>{W*ДЗЫНЬ*{x Накатило!</msgCharNoArgument>
  <msgCharNotFound></msgCharNotFound>
  <msgOthersAuto></msgOthersAuto>
  <msgOthersFound></msgOthersFound>
  <msgOthersFound2></msgOthersFound2>
  <msgOthersNoArgument>$c1 пол$gно|он|на идей!!</msgOthersNoArgument>
  <msgVictimFound></msgVictimFound>
  <msgVictimFound2></msgVictimFound2>
  <position>rest</position>
  <rusName>осенило</rusName>
  <shortDesc>демонстрация окружающим своей креативности</shortDesc>
</Social>
