<?xml version="1.0" encoding="UTF-8"?>
<Social type="Social">
  <msgCharAuto>Прекрати - не время и не место...</msgCharAuto>
  <msgCharFound>Ты глазами раздеваешь $C4...</msgCharFound>
  <msgCharFound2></msgCharFound2>
  <msgCharNoArgument>Ты начинаешь раздеваться... может кто-то заметит?</msgCharNoArgument>
  <msgCharNotFound>Не-ту...</msgCharNotFound>
  <msgOthersAuto></msgOthersAuto>
  <msgOthersFound>Ты видишь, что $c1 хочет $C4, и чувствуешь, как воздух в комнате нагревается.</msgOthersFound>
  <msgOthersFound2></msgOthersFound2>
  <msgOthersNoArgument>$c1 начинает раздеваться... $e выглядит очень сексуально...</msgOthersNoArgument>
  <msgVictimFound>Ты чувствуешь, как $c1 мысленно раздевает тебя своим взглядом...</msgVictimFound>
  <msgVictimFound2></msgVictimFound2>
  <position>rest</position>
  <rusName>раздевание</rusName>
  <shortDesc>раздеваться или раздевать кого-либо взглядом</shortDesc>
</Social>
